{"bill":{"bill_id":1771174,"change_hash":"59c65a12539af3dead17490d98cdbc5b","session_id":2041,"session":{"session_id":2041,"state_id":52,"year_start":2023,"year_end":2024,"prefile":0,"sine_die":0,"prior":0,"special":0,"session_tag":"Regular Session","session_title":"2023-2024 Regular Session","session_name":"118th Congress"},"url":"https:\/\/legiscan.com\/US\/bill\/HB3935\/2023","state_link":"https:\/\/www.congress.gov\/bill\/118th-congress\/house-bill\/3935\/all-info","completed":0,"status":2,"status_date":"2023-07-25","progress":[{"date":"2023-06-09","event":1},{"date":"2023-06-09","event":9},{"date":"2023-06-12","event":9},{"date":"2023-06-14","event":10},{"date":"2023-07-25","event":2}],"state":"US","state_id":52,"bill_number":"HB3935","bill_type":"B","bill_type_id":"1","body":"H","body_id":114,"current_body":"S","current_body_id":115,"title":"National Transportation Safety Board Amendments Act of 2023","description":"To amend title 49, United States Code, to reauthorize and improve the Federal Aviation Administration and other civil aviation programs, and for other purposes.","pending_committee_id":0,"committee":[],"referrals":[{"date":"2023-06-09","committee_id":2315,"chamber":"H","chamber_id":114,"name":"Transportation And Infrastructure"},{"date":"2023-06-12","committee_id":2549,"chamber":"H","chamber_id":114,"name":"Subcommittee on Aviation"}],"history":[{"date":"2023-06-09","action":"Introduced in House","chamber":"H","chamber_id":114,"importance":0},{"date":"2023-06-09","action":"Referred to the House Committee on Transportation and Infrastructure.","chamber":"H","chamber_id":114,"importance":1},{"date":"2023-06-12","action":"Referred to the Subcommittee on Aviation.","chamber":"H","chamber_id":114,"importance":1},{"date":"2023-06-13","action":"Subcommittee on Aviation Discharged","chamber":"H","chamber_id":114,"importance":0},{"date":"2023-06-13","action":"Committee Consideration and Mark-up Session Held","chamber":"H","chamber_id":114,"importance":0},{"date":"2023-06-14","action":"Ordered to be Reported (Amended) by the Yeas and Nays: 63 - 0.","chamber":"H","chamber_id":114,"importance":1},{"date":"2023-07-11","action":"Reported (Amended) by the Committee on Transportation and Infrastructure. H. Rept. 118-138.","chamber":"H","chamber_id":114,"importance":0},{"date":"2023-07-11","action":"Placed on the Union Calendar, Calendar No. 109.","chamber":"H","chamber_id":114,"importance":0},{"date":"2023-07-18","action":"Rules Committee Resolution H. Res. 597 Reported to House. Rule provides for consideration of H.R. 3935 and H.R. 3941. The resolution provides for consideration of H.R. 3935 and H.R. 3941 both under a structured rule with one hour of general debate. The resolution provides for a motion to recommit on each measure.","chamber":"H","chamber_id":114,"importance":0},{"date":"2023-07-19","action":"Considered under the provisions of rule H. Res. 597.","chamber":"H","chamber_id":114,"importance":0},{"date":"2023-07-19","action":"Rule provides for consideration of H.R. 3935 and H.R. 3941. The resolution provides for consideration of H.R. 3935 and H.R. 3941 both under a structured rule with one hour of general debate. The resolution provides for a motion to recommit on each measure.","chamber":"H","chamber_id":114,"importance":0},{"date":"2023-07-19","action":"House resolved itself into the Committee of the Whole House on the state of the Union pursuant to H. Res. 597 and Rule XVIII.","chamber":"H","chamber_id":114,"importance":0},{"date":"2023-07-19","action":"The Speaker designated the Honorable Andrew R. Garbarino to act as Chairman of the Committee.","chamber":"H","chamber_id":114,"importance":0},{"date":"2023-07-19","action":"GENERAL DEBATE - The Committee of the Whole proceeded with one hour of general debate on H.R. 3935.","chamber":"H","chamber_id":114,"importance":0},{"date":"2023-07-19","action":"H.Amdt.260 Amendment (A001) offered by Mr. Graves (MO). (consideration: CR H3802-3805; text: CR H3802-3805)","chamber":"H","chamber_id":114,"importance":0},{"date":"2023-07-19","action":"DEBATE - Pursuant to the provisions of H. Res. 597, the Committee of the Whole proceeded with 10 minutes of debate on the Graves (MO) amendment No. 1.","chamber":"H","chamber_id":114,"importance":0},{"date":"2023-07-19","action":"H.Amdt.260 On agreeing to the Graves (MO) amendment Agreed to by voice vote.","chamber":"H","chamber_id":114,"importance":0},{"date":"2023-07-19","action":"H.Amdt.261 Amendments en bloc (A002) offered by Mr. Graves (MO). (consideration: CR H3806-3808; text: CR H3806-3808)","chamber":"H","chamber_id":114,"importance":0},{"date":"2023-07-19","action":"DEBATE - Pursuant to the provisions of H. Res. 597, the Committee of the Whole proceeded with 30 minutes of debate on the Graves (MO) amendment en bloc No. 1.","chamber":"H","chamber_id":114,"importance":0},{"date":"2023-07-19","action":"H.Amdt.261 On agreeing to the Graves (MO) amendments Agreed to by voice vote.","chamber":"H","chamber_id":114,"importance":0},{"date":"2023-07-19","action":"H.Amdt.262 Amendments en bloc (A003) offered by Mr. Graves (MO). (consideration: CR H3808-3810; text: CR H3808-3810)","chamber":"H","chamber_id":114,"importance":0},{"date":"2023-07-19","action":"DEBATE - Pursuant to the provisions of H. Res. 597, the Committee of the Whole proceeded with 30 minutes of debate on the Graves (MO) amendment en bloc No. 2.","chamber":"H","chamber_id":114,"importance":0},{"date":"2023-07-19","action":"H.Amdt.262 On agreeing to the Graves (MO) amendments Agreed to by voice vote.","chamber":"H","chamber_id":114,"importance":0},{"date":"2023-07-19","action":"H.Amdt.263 Amendments en bloc (A004) offered by Mr. Graves (MO). (consideration: CR H3810-3814; text: CR H3810-3814)","chamber":"H","chamber_id":114,"importance":0},{"date":"2023-07-19","action":"DEBATE - Pursuant to the provisions of H. Res. 597, the Committee of the Whole proceeded with 30 minutes of debate on the Graves (MO) amendment en bloc No. 3.","chamber":"H","chamber_id":114,"importance":0},{"date":"2023-07-19","action":"H.Amdt.263 On agreeing to the Graves (MO) amendments Agreed to by voice vote.","chamber":"H","chamber_id":114,"importance":0},{"date":"2023-07-19","action":"H.Amdt.264 Amendment (A005) offered by Mr. Langworthy. (consideration: CR H3814-3816, H3841; text: CR H3814)","chamber":"H","chamber_id":114,"importance":0},{"date":"2023-07-19","action":"DEBATE - Pursuant to the provisions of H. Res. 597, the Committee of the Whole proceeded with 10 minutes of debate on the Langworthy amendment No. 10.","chamber":"H","chamber_id":114,"importance":0},{"date":"2023-07-19","action":"POSTPONED PROCEEDINGS - At the conclusion of debate on the Langworthy amendment No. 10, the Chair put the question on agreeing to the amendment and by voice vote, announced the noes had prevailed. Mr. Higgins (NY) demanded a recorded vote and the Chair postponed further proceedings until a time to be announced.","chamber":"H","chamber_id":114,"importance":0},{"date":"2023-07-19","action":"H.Amdt.265 Amendment (A006) offered by Mr. Donalds. (consideration: CR H3816-3817; text: CR H3816)","chamber":"H","chamber_id":114,"importance":0},{"date":"2023-07-19","action":"DEBATE - Pursuant to the provisions of H. Res. 597, the Committee of the Whole proceeded with 10 minutes of debate on the Donalds amendment No. 23.","chamber":"H","chamber_id":114,"importance":0},{"date":"2023-07-19","action":"H.Amdt.265 On agreeing to the Donalds amendment (A006) Agreed to by voice vote.","chamber":"H","chamber_id":114,"importance":0},{"date":"2023-07-19","action":"H.Amdt.266 Amendment (A007) offered by Mr. Feenstra. (consideration: CR H3817, H3841; text: CR H3817)","chamber":"H","chamber_id":114,"importance":0},{"date":"2023-07-19","action":"DEBATE - Pursuant to the provisions of H. Res. 597, the Committee of the Whole proceeded with 10 minutes of debate on the Feenstra amendment No. 27.","chamber":"H","chamber_id":114,"importance":0},{"date":"2023-07-19","action":"POSTPONED PROCEEDINGS - At the conclusion of debate on the Feenstra amendment No. 27, the Chair put the question on agreeing to the amendment and by voice vote, announced the ayes had prevailed. Mr. Larsen (WA) demanded a recorded vote and the Chair postponed further proceedings until a time to be announced.","chamber":"H","chamber_id":114,"importance":0},{"date":"2023-07-19","action":"H.Amdt.267 Amendment (A008) offered by Mr. Fitzpatrick. (consideration: CR H3817-3818, H3842-3843; text: CR H3817)","chamber":"H","chamber_id":114,"importance":0},{"date":"2023-07-19","action":"DEBATE - Pursuant to the provisions of H. Res. 597, the Committee of the Whole proceeded with 10 minutes of debate on the Fitzpatrick amendment No. 29.","chamber":"H","chamber_id":114,"importance":0},{"date":"2023-07-19","action":"POSTPONED PROCEEDINGS - At the conclusion of debate on the Fitzpatrick amendment No. 29, the Chair put the question on agreeing to the amendment and by voice vote, announced the ayes had prevailed. Mr. Fitzpatrick demanded a recorded vote and the Chair postponed further proceedings until a time to be announced.","chamber":"H","chamber_id":114,"importance":0},{"date":"2023-07-19","action":"H.Amdt.268 Amendment (A009) offered by Mr. Gosar. (consideration: CR H3818-3819, H3843; text: CR H3818)","chamber":"H","chamber_id":114,"importance":0},{"date":"2023-07-19","action":"DEBATE - Pursuant to the provisions of H. Res. 597, the Committee of the Whole proceeded with 10 minutes of debate on the Gosar amendment No. 33.","chamber":"H","chamber_id":114,"importance":0},{"date":"2023-07-19","action":"POSTPONED PROCEEDINGS - At the conclusion of debate on the Gosar amendment No. 33, the Chair put the question on agreeing to the amendment and by voice vote, announced the ayes had prevailed. Mr. Case demanded a recorded vote and the Chair postponed further proceedings until a time to be announced.","chamber":"H","chamber_id":114,"importance":0},{"date":"2023-07-19","action":"H.Amdt.269 Amendment (A010) offered by Mrs. Miller (IL). (consideration: CR H3819-3820, H3843-3844; text: CR H3819-3820)","chamber":"H","chamber_id":114,"importance":0},{"date":"2023-07-19","action":"DEBATE - Pursuant to the provisions of H. Res. 597, the Committee of the Whole proceeded with 10 minutes of debate on the Miller (IL) amendment No. 35.","chamber":"H","chamber_id":114,"importance":0},{"date":"2023-07-19","action":"POSTPONED PROCEEDINGS - At the conclusion of debate on the Miller (IL) amendment No. 35, the Chair put the question on agreeing to the amendment and by voice vote, announced the ayes had prevailed. Mr. Larsen (WA) demanded a recorded vote and the Chair postponed further proceedings until a time to be announced.","chamber":"H","chamber_id":114,"importance":0},{"date":"2023-07-19","action":"H.Amdt.270 Amendment (A011) offered by Mrs. Miller (IL). (consideration: CR H3820, H3844-3845; text: CR H3820)","chamber":"H","chamber_id":114,"importance":0},{"date":"2023-07-19","action":"DEBATE - Pursuant to the provisions of H. Res. 597, the Committee of the Whole proceeded with 10 minutes of debate on the Miller (IL) amendment No. 36.","chamber":"H","chamber_id":114,"importance":0},{"date":"2023-07-19","action":"POSTPONED PROCEEDINGS - At the conclusion of debate on the Miller (IL) amendment No. 36, the Chair put the question on agreeing to the amendment and by voice vote, announced the ayes had prevailed. Mr. Larsen (WA) demanded a recorded vote and the Chair postponed further proceedings until a time to be announced.","chamber":"H","chamber_id":114,"importance":0},{"date":"2023-07-19","action":"H.Amdt.271 Amendment (A012) offered by Mr. Huizenga. (consideration: CR H3820-3822, H3845; text: CR H3820)","chamber":"H","chamber_id":114,"importance":0},{"date":"2023-07-19","action":"DEBATE - Pursuant to the provisions of H. Res. 597, the Committee of the Whole proceeded with 10 minutes of debate on the Huizenga amendment No. 44.","chamber":"H","chamber_id":114,"importance":0},{"date":"2023-07-19","action":"POSTPONED PROCEEDINGS - At the conclusion of debate on the Huizenga amendment No. 44, the Chair put the question on agreeing to the amendment and by voice vote, announced the ayes had prevailed. Mr. Larsen (WA) demanded a recorded vote and the Chair postponed further proceedings until a time to be announced.","chamber":"H","chamber_id":114,"importance":0},{"date":"2023-07-19","action":"H.Amdt.272 Amendment (A013) offered by Mr. Issa. (consideration: CR H3822-3823, H3845-3846; text: CR H3822)","chamber":"H","chamber_id":114,"importance":0},{"date":"2023-07-19","action":"DEBATE - Pursuant to the provisions of H. Res. 597, the Committee of the Whole proceeded with 10 minutes of debate on the Issa amendment No. 47.","chamber":"H","chamber_id":114,"importance":0},{"date":"2023-07-19","action":"POSTPONED PROCEEDINGS - At the conclusion of debate on the Issa amendment No. 47, the Chair put the question on agreeing to the amendment and by voice vote, announced the ayes had prevailed. Mr. Cohen demanded a recorded vote and the Chair postponed further proceedings until a time to be announced.","chamber":"H","chamber_id":114,"importance":0},{"date":"2023-07-19","action":"H.Amdt.273 Amendment (A014) offered by Mr. Jackson (TX). (consideration: CR H3823-3824, H3846-3847; text: CR H3823)","chamber":"H","chamber_id":114,"importance":0},{"date":"2023-07-19","action":"DEBATE - Pursuant to the provisions of H. R. 597, the Committee of the Whole proceeded with 10 minutes of debate on the Jackson (TX) amendment No. 48.","chamber":"H","chamber_id":114,"importance":0},{"date":"2023-07-19","action":"POSTPONED PROCEEDINGS - At the conclusion of debate on the Jackson (TX) amendment No. 48, the Chair put the question on agreeing to the amendment and by voice vote, announced the ayes had prevailed. Mr. Cohen demanded a recorded vote and the Chair postponed further proceedings until a time to be announced.","chamber":"H","chamber_id":114,"importance":0},{"date":"2023-07-19","action":"H.Amdt.274 Amendment (A015) offered by Mr. Kean (NJ). (consideration: CR H3824-3825, H3847; text: CR H3824)","chamber":"H","chamber_id":114,"importance":0},{"date":"2023-07-19","action":"DEBATE - Pursuant to the provisions of H. Res. 597, the Committee of the Whole proceeded with 10 minutes of debate on the Kean (NJ) amendment No. 50.","chamber":"H","chamber_id":114,"importance":0},{"date":"2023-07-19","action":"POSTPONED PROCEEDINGS - At the conclusion of debate on the Kean (NJ) amendment No. 50, the Chair put the question on agreeing to the amendment and by voice vote, announced the ayes had prevailed. Mr. Cohen demanded a recorded vote and the Chair postponed further proceedings until a time to be announced.","chamber":"H","chamber_id":114,"importance":0},{"date":"2023-07-19","action":"H.Amdt.275 Amendment (A016) offered by Mr. LaMalfa. (consideration: CR H3825-3826; text: CR H3825)","chamber":"H","chamber_id":114,"importance":0},{"date":"2023-07-19","action":"DEBATE - Pursuant to the provisions of H. Res. 597, the Committee of the Whole proceeded with 10 minutes of debate on the LaMalfa amendment No. 53.","chamber":"H","chamber_id":114,"importance":0},{"date":"2023-07-19","action":"H.Amdt.275 On agreeing to the LaMalfa amendment (A016) Agreed to by voice vote.","chamber":"H","chamber_id":114,"importance":0},{"date":"2023-07-19","action":"H.Amdt.276 Amendment (A017) offered by Mr. McClintock. (consideration: CR H3826-3828, H3847-3848; text: CR H3826)","chamber":"H","chamber_id":114,"importance":0},{"date":"2023-07-19","action":"DEBATE - Pursuant to the provisions of H. Res. 597, the Committee of the Whole proceeded with 10 minutes of debate on the McClintock amendment No. 62.","chamber":"H","chamber_id":114,"importance":0},{"date":"2023-07-19","action":"POSTPONED PROCEEDINGS - At conclusion of debate on the McClintock amendment No. 62, the Chair put the question on agreeing to the amendment and by voice vote, announced that the ayes had prevailed. Mr. Johnson (SD) demanded a recorded vote and the Chair postponed further proceedings until a time to be announced.","chamber":"H","chamber_id":114,"importance":0},{"date":"2023-07-19","action":"H.Amdt.277 Amendment (A018) offered by Mrs. Miller (IL). (consideration: CR H3828, H3848-3849; text: CR H3828)","chamber":"H","chamber_id":114,"importance":0},{"date":"2023-07-19","action":"DEBATE - Pursuant to the provisions of H. Res. 597, the Committee of the Whole proceeded with 10 minutes of debate on the Miller (IL) amendment No. 64.","chamber":"H","chamber_id":114,"importance":0},{"date":"2023-07-19","action":"POSTPONED PROCEEDINGS - At conclusion of debate on the Miller (IL) amendment No. 64, the Chair put the question on agreeing to the amendment and by voice vote, announced that the ayes had prevailed. Mr. Cohen demanded a recorded vote and the Chair postponed further proceedings until a time to be announced.","chamber":"H","chamber_id":114,"importance":0},{"date":"2023-07-19","action":"H.Amdt.278 Amendment (A019) offered by Mrs. Miller (IL). (consideration: CR H3828-3829, H3849; text: CR H3828)","chamber":"H","chamber_id":114,"importance":0},{"date":"2023-07-19","action":"DEBATE - Pursuant to the provisions of H. Res. 597, the Committee of the Whole proceeded with 10 minutes of debate on the Miller (IL) amendment No. 65.","chamber":"H","chamber_id":114,"importance":0},{"date":"2023-07-19","action":"POSTPONED PROCEEDINGS - At conclusion of debate on the Miller (IL) amendment No. 65, the Chair put the question on agreeing to the amendment and by voice vote, announced that the ayes had prevailed. Mr. Cohen demanded a recorded vote and the Chair postponed further proceedings until a time to be announced.","chamber":"H","chamber_id":114,"importance":0},{"date":"2023-07-19","action":"H.Amdt.279 Amendment (A020) offered by Mr. Obernolte. (consideration: CR H3829-3830; text: CR H3829)","chamber":"H","chamber_id":114,"importance":0},{"date":"2023-07-19","action":"DEBATE - Pursuant to the provisions of H. Res. 597, the Committee of the Whole proceeded with 10 minutes of debate on the Obernolte amendment No. 67.","chamber":"H","chamber_id":114,"importance":0},{"date":"2023-07-19","action":"H.Amdt.279 On agreeing to the Obernolte amendment (A020) Agreed to by voice vote.","chamber":"H","chamber_id":114,"importance":0},{"date":"2023-07-19","action":"H.Amdt.280 Amendment (A021) offered by Mr. Obernolte. (consideration: CR H3830-3831, H3849-3850; text: CR H3830)","chamber":"H","chamber_id":114,"importance":0},{"date":"2023-07-19","action":"DEBATE - Pursuant to the provisions of H. Res. 597, the Committee of the Whole proceeded with 10 minutes of debate on the Obernolte amendment No. 68.","chamber":"H","chamber_id":114,"importance":0},{"date":"2023-07-19","action":"POSTPONED PROCEEDINGS - At conclusion of debate on the Obernolte amendment No. 68, the Chair put the question on agreeing to the amendment and by voice vote, announced that the ayes had prevailed. Mr. Johnson (GA) demanded a recorded vote and the Chair postponed further proceedings until a time to be announced.","chamber":"H","chamber_id":114,"importance":0},{"date":"2023-07-19","action":"H.Amdt.281 Amendment (A022) offered by Mr. Ogles. (consideration: CR H3831-3832, H3850-3851; text: CR H3831)","chamber":"H","chamber_id":114,"importance":0},{"date":"2023-07-19","action":"DEBATE - Pursuant to the provisions of H. Res. 597, the Committee of the Whole proceeded with 10 minutes of debate on the Ogles amendment No. 69.","chamber":"H","chamber_id":114,"importance":0},{"date":"2023-07-19","action":"POSTPONED PROCEEDINGS - At conclusion of debate on the Ogles amendment No. 69, the Chair put the question on agreeing to the amendment and by voice vote, announced that the ayes had prevailed. Mr. Johnson (GA) demanded a recorded vote and the Chair postponed further proceedings until a time to be announced.","chamber":"H","chamber_id":114,"importance":0},{"date":"2023-07-19","action":"H.Amdt.282 Amendment (A023) offered by Mr. Ogles. (consideration: CR H3832-3833, H3851; text: CR H3832)","chamber":"H","chamber_id":114,"importance":0},{"date":"2023-07-19","action":"DEBATE - Pursuant to the provisions of H. Res. 597, the Committee of the Whole proceeded with 10 minutes of debate on the Ogles amendment No. 70.","chamber":"H","chamber_id":114,"importance":0},{"date":"2023-07-19","action":"POSTPONED PROCEEDINGS - At conclusion of debate on the Ogles amendment No. 70, the Chair put the question on agreeing to the amendment and by voice vote, announced that the ayes had prevailed. Mr. Johnson (GA) demanded a recorded vote and the Chair postponed further proceedings until a time to be announced.","chamber":"H","chamber_id":114,"importance":0},{"date":"2023-07-19","action":"H.Amdt.283 Amendment (A024) offered by Mr. Owens. (consideration: CR H3833-3835, H3851-3852; text: CR H3833)","chamber":"H","chamber_id":114,"importance":0},{"date":"2023-07-19","action":"DEBATE - Pursuant to the provisions of H. Res. 597, the Committee of the Whole proceeded with 10 minutes of debate on the Owens amendment No. 71.","chamber":"H","chamber_id":114,"importance":0},{"date":"2023-07-19","action":"POSTPONED PROCEEDINGS - At conclusion of debate on the Owens amendment No. 71, the Chair put the question on agreeing to the amendment and by voice vote, announced that the ayes had prevailed. Mr. Larsen (WA) demanded a recorded vote and the Chair postponed further proceedings until a time to be announced.","chamber":"H","chamber_id":114,"importance":0},{"date":"2023-07-19","action":"H.Amdt.284 Amendment (A025) offered by Mr. Perry. (consideration: CR H3835-3836, H3852-3853; text: CR H3835)","chamber":"H","chamber_id":114,"importance":0},{"date":"2023-07-19","action":"DEBATE - Pursuant to the provisions of H. Res. 597, the Committee of the Whole proceeded with 10 minutes of debate on the Perry amendment No. 73.","chamber":"H","chamber_id":114,"importance":0},{"date":"2023-07-19","action":"POSTPONED PROCEEDINGS - At the conclusion of debate on the Perry amendment No. 73, the Chair put the question on agreeing to the amendment and by voice vote, announced that the ayes had prevailed. Mr. Larsen (WA) demanded a recorded vote and the Chair postponed further proceedings until a time to be announced.","chamber":"H","chamber_id":114,"importance":0},{"date":"2023-07-19","action":"H.Amdt.285 Amendment (A026) offered by Mr. Perry. (consideration: CR H3836-3837, H3853; text: CR H3836)","chamber":"H","chamber_id":114,"importance":0},{"date":"2023-07-19","action":"DEBATE - Pursuant to the provisions of H. Res. 597, the Committee of the Whole proceeded with 10 minutes of debate on the Perry amendment No. 74.","chamber":"H","chamber_id":114,"importance":0},{"date":"2023-07-19","action":"POSTPONED PROCEEDINGS - At the conclusion of debate on the Perry amendment No. 74, the Chair put the question on agreeing to the amendment and by voice vote, announced that the ayes had prevailed. Mr. Johnson (GA) demanded a recorded vote and the Chair postponed further proceedings until a time to be announced.","chamber":"H","chamber_id":114,"importance":0},{"date":"2023-07-19","action":"H.Amdt.286 Amendment (A027) offered by Mr. Perry. (consideration: CR H3837-3838, H3853-3854; text: CR H3837)","chamber":"H","chamber_id":114,"importance":0},{"date":"2023-07-19","action":"DEBATE - Pursuant to the provisions of H. Res. 597, the Committee of the Whole proceeded with 10 minutes of debate on the Perry amendment No. 75.","chamber":"H","chamber_id":114,"importance":0},{"date":"2023-07-19","action":"POSTPONED PROCEEDINGS - At the conclusion of debate on the Perry amendment No. 75, the Chair put the question on agreeing to the amendment and by voice vote, announced the ayes had prevailed. Mr. Johnson (GA) demanded a recorded vote and the Chair postponed further proceedings until a time to be announced.","chamber":"H","chamber_id":114,"importance":0},{"date":"2023-07-19","action":"Mr. Perry moved that the committee rise.","chamber":"H","chamber_id":114,"importance":0},{"date":"2023-07-19","action":"On motion that the committee rise Agreed to by voice vote.","chamber":"H","chamber_id":114,"importance":0},{"date":"2023-07-19","action":"Committee of the Whole House on the state of the Union rises leaving H.R. 3935 as unfinished business.","chamber":"H","chamber_id":114,"importance":0},{"date":"2023-07-19","action":"Considered as unfinished business.","chamber":"H","chamber_id":114,"importance":0},{"date":"2023-07-19","action":"The House resolved into Committee of the Whole House on the state of the Union for further consideration.","chamber":"H","chamber_id":114,"importance":0},{"date":"2023-07-19","action":"H.Amdt.264 On agreeing to the Langworthy amendment (A005) Agreed to by recorded vote: 243 - 191 (Roll no. 341).","chamber":"H","chamber_id":114,"importance":0},{"date":"2023-07-19","action":"H.Amdt.266 On agreeing to the Feenstra amendment (A007) Failed by recorded vote: 203 - 231 (Roll no. 342).","chamber":"H","chamber_id":114,"importance":0},{"date":"2023-07-19","action":"H.Amdt.267 On agreeing to the Fitzpatrick amendment (A008) Agreed to by recorded vote: 392 - 41 (Roll no. 343).","chamber":"H","chamber_id":114,"importance":0},{"date":"2023-07-19","action":"H.Amdt.268 On agreeing to the Gosar amendment (A009) Failed by recorded vote: 193 - 236 (Roll no. 344).","chamber":"H","chamber_id":114,"importance":0},{"date":"2023-07-19","action":"H.Amdt.269 On agreeing to the Miller (IL) amendment (A010) Failed by recorded vote: 177 - 258 (Roll no. 345).","chamber":"H","chamber_id":114,"importance":0},{"date":"2023-07-19","action":"H.Amdt.270 On agreeing to the Miller (IL) amendment (A011) Failed by recorded vote: 141 - 294 (Roll no. 346).","chamber":"H","chamber_id":114,"importance":0},{"date":"2023-07-19","action":"H.Amdt.271 On agreeing to the Huizenga amendment (A012) Agreed to by recorded vote: 220 - 215 (Roll no. 347).","chamber":"H","chamber_id":114,"importance":0},{"date":"2023-07-19","action":"H.Amdt.272 On agreeing to the Issa amendment (A013) Failed by recorded vote: 214 - 219 (Roll no. 348).","chamber":"H","chamber_id":114,"importance":0},{"date":"2023-07-19","action":"H.Amdt.273 On agreeing to the Jackson (TX) amendment (A014) Failed by recorded vote: 211 - 224 (Roll no. 349).","chamber":"H","chamber_id":114,"importance":0},{"date":"2023-07-19","action":"H.Amdt.274 On agreeing to the Kean (NJ) amendment (A015) Agreed to by recorded vote: 240 - 195 (Roll no. 350).","chamber":"H","chamber_id":114,"importance":0},{"date":"2023-07-19","action":"H.Amdt.276 On agreeing to the McClintock amendment (A017) Failed by recorded vote: 49 - 386 (Roll no. 351).","chamber":"H","chamber_id":114,"importance":0},{"date":"2023-07-19","action":"H.Amdt.277 On agreeing to the Miller (IL) amendment (A018) Failed by recorded vote: 216 - 219 (Roll no. 352).","chamber":"H","chamber_id":114,"importance":0},{"date":"2023-07-19","action":"H.Amdt.278 On agreeing to the Miller (IL) amendment (A019) Failed by recorded vote: 181 - 254 (Roll no. 353).","chamber":"H","chamber_id":114,"importance":0},{"date":"2023-07-19","action":"H.Amdt.280 On agreeing to the Obernolte amendment (A021) Agreed to by recorded vote: 229 - 205 (Roll no. 354).","chamber":"H","chamber_id":114,"importance":0},{"date":"2023-07-19","action":"H.Amdt.281 On agreeing to the Ogles amendment (A022) Failed by recorded vote: 191 - 244 (Roll no. 355).","chamber":"H","chamber_id":114,"importance":0},{"date":"2023-07-19","action":"H.Amdt.282 On agreeing to the Ogles amendment (A023) Failed by recorded vote: 206 - 227 (Roll no. 356).","chamber":"H","chamber_id":114,"importance":0},{"date":"2023-07-19","action":"H.Amdt.283 On agreeing to the Owens amendment (A024) Failed by recorded vote: 205 - 229 (Roll no. 357).","chamber":"H","chamber_id":114,"importance":0},{"date":"2023-07-19","action":"H.Amdt.284 On agreeing to the Perry amendment (A025) Failed by recorded vote: 127 - 308 (Roll no. 358).","chamber":"H","chamber_id":114,"importance":0},{"date":"2023-07-19","action":"H.Amdt.285 On agreeing to the Perry amendment (A026) Failed by recorded vote: 52 - 381 (Roll no. 359).","chamber":"H","chamber_id":114,"importance":0},{"date":"2023-07-19","action":"H.Amdt.286 On agreeing to the Perry amendment (A027) Failed by recorded vote: 45 - 387 (Roll no. 360).","chamber":"H","chamber_id":114,"importance":0},{"date":"2023-07-19","action":"Mr. Graves (MO) moved that the committee rise.","chamber":"H","chamber_id":114,"importance":0},{"date":"2023-07-19","action":"On motion that the committee rise Agreed to by voice vote.","chamber":"H","chamber_id":114,"importance":0},{"date":"2023-07-19","action":"Committee of the Whole House on the state of the Union rises leaving H.R. 3935 as unfinished business.","chamber":"H","chamber_id":114,"importance":0},{"date":"2023-07-20","action":"Considered as unfinished business.","chamber":"H","chamber_id":114,"importance":0},{"date":"2023-07-20","action":"The House resolved into Committee of the Whole House on the state of the Union for further consideration.","chamber":"H","chamber_id":114,"importance":0},{"date":"2023-07-20","action":"H.Amdt.287 Amendments en bloc (A028) offered by Mr. Graves (MO). (consideration: CR H3863-3868, H3871-3872; text: CR H3863-3866)","chamber":"H","chamber_id":114,"importance":0},{"date":"2023-07-20","action":"DEBATE - Pursuant to the provisions of H. Res. 597, the Committee of the Whole proceeded with 30 minutes of debate on the Graves (MO) amendment en bloc No. 4.","chamber":"H","chamber_id":114,"importance":0},{"date":"2023-07-20","action":"POSTPONED PROCEEDINGS - At the conclusion of debate on the Graves (MO) amendment en bloc No. 4, the Chair put the question on agreeing to the amendment and by voice vote, announced the ayes had prevailed. Mr. Larsen (WA) demanded a recorded vote and the Chair postponed further proceedings until a time to be announced.","chamber":"H","chamber_id":114,"importance":0},{"date":"2023-07-20","action":"H.Amdt.288 Amendment (A029) offered by Mr. Perry. (consideration: CR H3868-3869, H3872; text: CR H3868)","chamber":"H","chamber_id":114,"importance":0},{"date":"2023-07-20","action":"DEBATE - Pursuant to the provisions of H. Res. 597, the Committee of the Whole proceeded with 10 minutes of debate on the Perry amendment No. 76.","chamber":"H","chamber_id":114,"importance":0},{"date":"2023-07-20","action":"POSTPONED PROCEEDINGS - At the conclusion of debate on the Perry amendment No. 76, the Chair put the question on agreeing to the amendment and by voice vote, announced the ayes had prevailed. Mr. Graves (MO) demanded a recorded vote and the Chair postponed further proceedings until a time to be announced.","chamber":"H","chamber_id":114,"importance":0},{"date":"2023-07-20","action":"H.Amdt.289 Amendment (A030) offered by Mr. Perry. (consideration: CR H3869-3871, H3872-3873; text: CR H3869)","chamber":"H","chamber_id":114,"importance":0},{"date":"2023-07-20","action":"DEBATE - Pursuant to the provisions of H. Res. 597, the Committee of the Whole proceeded with 10 minutes of debate on the Perry amendment No. 77.","chamber":"H","chamber_id":114,"importance":0},{"date":"2023-07-20","action":"POSTPONED PROCEEDINGS - At the conclusion of debate on the Perry amendment No. 77, the Chair put the question on agreeing to the amendment and by voice vote, announced the ayes had prevailed. Mr. Larsen (WA) demanded a recorded vote and the Chair postponed further proceedings until a time to be announced.","chamber":"H","chamber_id":114,"importance":0},{"date":"2023-07-20","action":"H.Amdt.287 On agreeing to the Graves (MO) amendments Agreed to by recorded vote: 348 - 57 (Roll no. 361).","chamber":"H","chamber_id":114,"importance":0},{"date":"2023-07-20","action":"H.Amdt.288 On agreeing to the Perry amendment (A029) Failed by recorded vote: 64 - 329 (Roll no. 362).","chamber":"H","chamber_id":114,"importance":0},{"date":"2023-07-20","action":"H.Amdt.289 On agreeing to the Perry amendment (A030) Failed by recorded vote: 195 - 226 (Roll no. 363).","chamber":"H","chamber_id":114,"importance":0},{"date":"2023-07-20","action":"The House rose from the Committee of the Whole House on the state of the Union to report H.R. 3935.","chamber":"H","chamber_id":114,"importance":0},{"date":"2023-07-20","action":"The previous question was ordered pursuant to the rule.","chamber":"H","chamber_id":114,"importance":0},{"date":"2023-07-20","action":"The House adopted the amendments en gross as agreed to by the Committee of the Whole House on the state of the Union.","chamber":"H","chamber_id":114,"importance":0},{"date":"2023-07-20","action":"On passage Passed by the Yeas and Nays: 351 - 69 (Roll no. 364).","chamber":"H","chamber_id":114,"importance":0},{"date":"2023-07-20","action":"Motion to reconsider laid on the table Agreed to without objection.","chamber":"H","chamber_id":114,"importance":0},{"date":"2023-07-20","action":"The Clerk was authorized to correct section numbers, punctuation, and cross references, and to make other necessary technical and conforming corrections in the engrossment of H.R. 3935.","chamber":"H","chamber_id":114,"importance":0},{"date":"2023-07-25","action":"Received in the Senate.","chamber":"S","chamber_id":115,"importance":1},{"date":"2023-09-20","action":"Read the first time. Placed on Senate Legislative Calendar under Read the First Time.","chamber":"S","chamber_id":115,"importance":0},{"date":"2023-09-21","action":"Read the second time. Placed on Senate Legislative Calendar under General Orders. Calendar No. 211.","chamber":"S","chamber_id":115,"importance":0},{"date":"2023-09-21","action":"Motion to proceed to consideration of measure made in Senate. (CR S4665)","chamber":"S","chamber_id":115,"importance":0},{"date":"2023-09-21","action":"Cloture motion on the motion to proceed to the measure presented in Senate. (CR S4665)","chamber":"S","chamber_id":115,"importance":0},{"date":"2023-09-26","action":"Motion to proceed to measure considered in Senate. (CR S4669)","chamber":"S","chamber_id":115,"importance":0},{"date":"2023-09-26","action":"Cloture on the motion to proceed to the measure invoked in Senate by Yea-Nay Vote. 77 - 19. Record Vote Number: 240.","chamber":"S","chamber_id":115,"importance":0},{"date":"2023-09-27","action":"Motion to proceed to measure considered in Senate. (CR S4689)","chamber":"S","chamber_id":115,"importance":0},{"date":"2023-09-28","action":"Motion to proceed to measure considered in Senate. (CR S4729)","chamber":"S","chamber_id":115,"importance":0},{"date":"2023-09-28","action":"Motion to proceed to consideration of measure agreed to in Senate by Yea-Nay Vote. 76 - 22. Record Vote Number: 241.","chamber":"S","chamber_id":115,"importance":0},{"date":"2023-09-28","action":"Measure laid before Senate by motion. (consideration: CR S4729-4739)","chamber":"S","chamber_id":115,"importance":0},{"date":"2023-09-28","action":"Motion by Senator Schumer to commit to Senate Committee on Commerce, Science, and Transportation with instructions to report back forthwith with the following amendment (SA 1294) made in Senate.","chamber":"S","chamber_id":115,"importance":0},{"date":"2023-09-28","action":"S.Amdt.1295 Amendment SA 1295 proposed by Senator Schumer to Amendment SA 1294 (the instructions of the motion to commit). (consideration: CR S4734) To modify the effective date.","chamber":"S","chamber_id":115,"importance":0},{"date":"2023-09-28","action":"S.Amdt.1292 Amendment SA 1292 proposed by Senator Schumer for Senator Murray. (consideration: CR S4733) In the nature of a substitute.","chamber":"S","chamber_id":115,"importance":0},{"date":"2023-09-28","action":"S.Amdt.1293 Amendment SA 1293 proposed by Senator Schumer to Amendment SA 1292. (consideration: CR S4733-4734) To add an effective date.","chamber":"S","chamber_id":115,"importance":0},{"date":"2023-09-28","action":"S.Amdt.1292 Cloture motion on amendment SA1292 presented in Senate.","chamber":"S","chamber_id":115,"importance":0},{"date":"2023-09-28","action":"S.Amdt.1294 Amendment SA 1294 proposed by Senator Schumer. (consideration: CR S4734) To add an effective date.","chamber":"S","chamber_id":115,"importance":0},{"date":"2023-09-28","action":"Cloture motion on the measure presented in Senate. (consideration: CR S4734; text: CR S4734)","chamber":"S","chamber_id":115,"importance":0},{"date":"2023-09-29","action":"S.Amdt.1292 Considered by Senate. (consideration: CR S4806)","chamber":"S","chamber_id":115,"importance":0},{"date":"2023-09-29","action":"S.Amdt.1294 Considered by Senate. (consideration: CR S4806)","chamber":"S","chamber_id":115,"importance":0},{"date":"2023-09-29","action":"S.Amdt.1293 Considered by Senate. (consideration: CR S4806)","chamber":"S","chamber_id":115,"importance":0},{"date":"2023-09-29","action":"S.Amdt.1295 Considered by Senate. (consideration: CR S4806)","chamber":"S","chamber_id":115,"importance":0},{"date":"2023-09-29","action":"Considered by Senate. (consideration: CR S4806, S4818-4820)","chamber":"S","chamber_id":115,"importance":0},{"date":"2023-09-30","action":"Considered by Senate. (consideration: CR S4885)","chamber":"S","chamber_id":115,"importance":0},{"date":"2023-09-30","action":"S.Amdt.1292 Cloture motion on amendment SA1292 withdrawn by unanimous consent in Senate.","chamber":"S","chamber_id":115,"importance":0},{"date":"2023-09-30","action":"S.Amdt.1292 Considered by Senate. (consideration: CR S4885)","chamber":"S","chamber_id":115,"importance":0},{"date":"2023-09-30","action":"S.Amdt.1293 Considered by Senate. (consideration: CR S4885)","chamber":"S","chamber_id":115,"importance":0},{"date":"2023-09-30","action":"S.Amdt.1294 Considered by Senate. (consideration: CR S4885)","chamber":"S","chamber_id":115,"importance":0},{"date":"2023-09-30","action":"S.Amdt.1295 Considered by Senate. (consideration: CR S4885)","chamber":"S","chamber_id":115,"importance":0},{"date":"2023-09-30","action":"Cloture motion on the measure withdrawn by unanimous consent in Senate. (CR S4885)","chamber":"S","chamber_id":115,"importance":0},{"date":"2024-04-20","action":"Motion to proceed to consideration of measure made in Senate. (CR S2928)","chamber":"S","chamber_id":115,"importance":0},{"date":"2024-04-20","action":"Motion to proceed to measure considered in Senate. (CR S2941)","chamber":"S","chamber_id":115,"importance":0},{"date":"2024-04-23","action":"Motion to proceed to measure considered in Senate. (CR S2943)","chamber":"S","chamber_id":115,"importance":0},{"date":"2024-04-23","action":"Cloture motion on the motion to proceed to the measure presented in Senate.","chamber":"S","chamber_id":115,"importance":0},{"date":"2024-05-01","action":"Motion to proceed to measure considered in Senate. (CR S3107)","chamber":"S","chamber_id":115,"importance":0},{"date":"2024-05-01","action":"Cloture on the motion to proceed to the measure invoked in Senate by Yea-Nay Vote. 89 - 10. Record Vote Number: 157. (CR S3111)","chamber":"S","chamber_id":115,"importance":0},{"date":"2024-05-02","action":"Motion to proceed to measure considered in Senate. (CR S3295)","chamber":"S","chamber_id":115,"importance":0},{"date":"2024-05-02","action":"Motion to proceed to consideration of measure agreed to in Senate by Yea-Nay Vote. 81 - 10. Record Vote Number: 158.","chamber":"S","chamber_id":115,"importance":0},{"date":"2024-05-02","action":"S.Amdt.1294 Considered by Senate. (consideration: CR S3305)","chamber":"S","chamber_id":115,"importance":0},{"date":"2024-05-02","action":"S.Amdt.1292 Considered by Senate. (consideration: CR S3305)","chamber":"S","chamber_id":115,"importance":0},{"date":"2024-05-02","action":"S.Amdt.1293 Considered by Senate. (consideration: CR S3305)","chamber":"S","chamber_id":115,"importance":0},{"date":"2024-05-02","action":"S.Amdt.1295 Considered by Senate. (consideration: CR S3305)","chamber":"S","chamber_id":115,"importance":0},{"date":"2024-05-02","action":"Measure laid before Senate by motion. (consideration: CR S3305)","chamber":"S","chamber_id":115,"importance":0},{"date":"2024-05-07","action":"Considered by Senate. (consideration: CR S3381-3496)","chamber":"S","chamber_id":115,"importance":0},{"date":"2024-05-07","action":"Motion by Senator Schumer to commit to Senate Committee on Commerce, Science, and Transportation with instructions to report back forthwith with the following amendment (SA 1294) tabled in Senate by Voice Vote.","chamber":"S","chamber_id":115,"importance":0},{"date":"2024-05-07","action":"Motion by Senator Schumer to commit to Senate Committee on Commerce, Science, and Transportation with instructions to report back forthwith with the following amendment (SA 2027) made in Senate. (text: CR S3495)","chamber":"S","chamber_id":115,"importance":0},{"date":"2024-05-07","action":"S.Amdt.1293 Considered by Senate. (consideration: CR S3381)","chamber":"S","chamber_id":115,"importance":0},{"date":"2024-05-07","action":"S.Amdt.1292 Motion to table amendment SA 1292 agreed to in Senate by Voice Vote.","chamber":"S","chamber_id":115,"importance":0},{"date":"2024-05-07","action":"S.Amdt.1293 SA 1293 fell when SA 1292 was tabled.","chamber":"S","chamber_id":115,"importance":0},{"date":"2024-05-07","action":"S.Amdt.1294 Considered by Senate. (consideration: CR S3381)","chamber":"S","chamber_id":115,"importance":0},{"date":"2024-05-07","action":"S.Amdt.1911 Amendment SA 1911 proposed by Senator Schumer for Senator Cantwell. (consideration: CR S3381) In the nature of a substitute.","chamber":"S","chamber_id":115,"importance":0},{"date":"2024-05-07","action":"S.Amdt.1911 Cloture motion on amendment SA1911, as modified, presented in Senate. (CR S3496)","chamber":"S","chamber_id":115,"importance":0},{"date":"2024-05-07","action":"S.Amdt.1295 SA 1295 fell when SA 1294 was tabled.","chamber":"S","chamber_id":115,"importance":0},{"date":"2024-05-07","action":"S.Amdt.1295 Considered by Senate. (consideration: CR S3381)","chamber":"S","chamber_id":115,"importance":0},{"date":"2024-05-07","action":"S.Amdt.1294 Motion to table amendment SA 1294 agreed to in Senate by Voice Vote.","chamber":"S","chamber_id":115,"importance":0},{"date":"2024-05-07","action":"S.Amdt.1292 Considered by Senate. (consideration: CR S3381)","chamber":"S","chamber_id":115,"importance":0},{"date":"2024-05-07","action":"S.Amdt.2026 Amendment SA 2026 proposed by Senator Schumer to Amendment SA 1911 (as modified). (consideration: CR S3495) To add an effective date.","chamber":"S","chamber_id":115,"importance":0},{"date":"2024-05-07","action":"S.Amdt.2028 Amendment SA 2028 proposed by Senator Schumer to Amendment SA 2027 (the instructions of the motion to commit). (consideration: CR S3496) To add an effective date.","chamber":"S","chamber_id":115,"importance":0},{"date":"2024-05-07","action":"S.Amdt.2027 Amendment SA 2027 proposed by Senator Schumer. (consideration: CR S3495) To add an effective date.","chamber":"S","chamber_id":115,"importance":0},{"date":"2024-05-07","action":"S.Amdt.2029 Amendment SA 2029 proposed by Senator Schumer to Amendment SA 2028. (consideration: CR S3496) To add an effective date.","chamber":"S","chamber_id":115,"importance":0},{"date":"2024-05-07","action":"Cloture motion on the measure presented in Senate. (CR S3496)","chamber":"S","chamber_id":115,"importance":0},{"date":"2024-05-08","action":"Considered by Senate. (consideration: CR S3567-3589)","chamber":"S","chamber_id":115,"importance":0},{"date":"2024-05-08","action":"S.Amdt.2027 Considered by Senate.","chamber":"S","chamber_id":115,"importance":0},{"date":"2024-05-08","action":"S.Amdt.2026 Considered by Senate.","chamber":"S","chamber_id":115,"importance":0},{"date":"2024-05-08","action":"S.Amdt.1911 Considered by Senate.","chamber":"S","chamber_id":115,"importance":0},{"date":"2024-05-08","action":"S.Amdt.2028 Considered by Senate.","chamber":"S","chamber_id":115,"importance":0},{"date":"2024-05-08","action":"S.Amdt.2029 Considered by Senate.","chamber":"S","chamber_id":115,"importance":0},{"date":"2024-05-08","action":"Motion to table the motion by Senator Schumer to commit the bill (H.R. 3935) to Senate Committee on Commerce, Science, and Transportation with instructions to report back forthwith with amendment SA 2027 rejected in Senate by Yea-Nay Vote. 12 - 85. Record Vote Number: 160.","chamber":"S","chamber_id":115,"importance":0},{"date":"2024-05-09","action":"Considered by Senate.","chamber":"S","chamber_id":115,"importance":0},{"date":"2024-05-09","action":"Cloture on SA 1911, as modified, invoked in Senate by Yea-Nay Vote. 84 - 13. Record Vote Number: 161.","chamber":"S","chamber_id":115,"importance":0},{"date":"2024-05-09","action":"Motion by Senator Schumer to commit to Senate Committee on Commerce, Science, and Transportation with instructions to report back forthwith with the following amendment (SA 2027) fell when cloture was invoked on SA 1911, as modified, in Senate.","chamber":"S","chamber_id":115,"importance":0},{"date":"2024-05-09","action":"S.Amdt.2029 SA 2029 fell when SA 2028 fell.","chamber":"S","chamber_id":115,"importance":0},{"date":"2024-05-09","action":"S.Amdt.2040 Amendment SA 2040 proposed by Senator Schumer. To add an effective date.","chamber":"S","chamber_id":115,"importance":0},{"date":"2024-05-09","action":"S.Amdt.2029 Considered by Senate.","chamber":"S","chamber_id":115,"importance":0},{"date":"2024-05-09","action":"S.Amdt.2041 Amendment SA 2041 proposed by Senator Cantwell for Senator Schumer to Amendment SA 2040. To add an effective date.","chamber":"S","chamber_id":115,"importance":0},{"date":"2024-05-09","action":"S.Amdt.2041 SA 2041 fell when SA 2040 was withdrawn.","chamber":"S","chamber_id":115,"importance":0},{"date":"2024-05-09","action":"S.Amdt.2028 SA 2028 fell when SA 2027 (the instructions of the motion to commit) fell.","chamber":"S","chamber_id":115,"importance":0},{"date":"2024-05-09","action":"S.Amdt.2040 Proposed amendment SA 2040 withdrawn in Senate.","chamber":"S","chamber_id":115,"importance":0},{"date":"2024-05-09","action":"S.Amdt.2027 SA 2027 fell when cloture invoked on SA 1911, as modified.","chamber":"S","chamber_id":115,"importance":0},{"date":"2024-05-09","action":"S.Amdt.1911 Amendment SA 1911 as modified agreed to in Senate by Voice Vote.","chamber":"S","chamber_id":115,"importance":0},{"date":"2024-05-09","action":"S.Amdt.1911 Considered by Senate. (consideration: CR S3629, S3645)","chamber":"S","chamber_id":115,"importance":0},{"date":"2024-05-09","action":"S.Amdt.2026 Considered by Senate.","chamber":"S","chamber_id":115,"importance":0},{"date":"2024-05-09","action":"S.Amdt.2026 Proposed amendment SA 2026 withdrawn in Senate.","chamber":"S","chamber_id":115,"importance":0},{"date":"2024-05-09","action":"S.Amdt.2028 Considered by Senate.","chamber":"S","chamber_id":115,"importance":0},{"date":"2024-05-09","action":"S.Amdt.2027 Considered by Senate.","chamber":"S","chamber_id":115,"importance":0},{"date":"2024-05-09","action":"Passed Senate, under the order of 5\/9\/2024, having achieved 60 votes in the affirmative with an amendment by Yea-Nay Vote. 88 - 4. Record Vote Number: 162.","chamber":"S","chamber_id":115,"importance":0}],"sponsors":[{"people_id":9273,"person_hash":"qxalf223","party_id":"2","state_id":52,"party":"R","role_id":1,"role":"Rep","name":"Sam Graves","first_name":"Sam","middle_name":"","last_name":"Graves","suffix":"","nickname":"","district":"HD-MO-6","ftm_eid":3836803,"votesmart_id":9425,"opensecrets_id":"N00013323","knowwho_pid":195969,"ballotpedia":"Sam_Graves","bioguide_id":"G000546","sponsor_type_id":1,"sponsor_order":1,"committee_sponsor":0,"committee_id":0,"state_federal":0},{"people_id":9076,"person_hash":"31giymui","party_id":"1","state_id":52,"party":"D","role_id":1,"role":"Rep","name":"Rick Larsen","first_name":"Rick","middle_name":"","last_name":"Larsen","suffix":"","nickname":"","district":"HD-WA-2","ftm_eid":17657616,"votesmart_id":56231,"opensecrets_id":"N00009759","knowwho_pid":124078,"ballotpedia":"Rick_Larsen","bioguide_id":"L000560","sponsor_type_id":2,"sponsor_order":2,"committee_sponsor":0,"committee_id":0,"state_federal":0},{"people_id":16503,"person_hash":"4z13x8m3","party_id":"2","state_id":52,"party":"R","role_id":1,"role":"Rep","name":"Garret Graves","first_name":"Garret","middle_name":"","last_name":"Graves","suffix":"","nickname":"","district":"HD-LA-6","ftm_eid":26395838,"votesmart_id":155424,"opensecrets_id":"N00036135","knowwho_pid":160828,"ballotpedia":"Garret_Graves","bioguide_id":"G000577","sponsor_type_id":2,"sponsor_order":3,"committee_sponsor":0,"committee_id":0,"state_federal":0},{"people_id":9025,"person_hash":"0flzaozy","party_id":"1","state_id":52,"party":"D","role_id":1,"role":"Rep","name":"Steve Cohen","first_name":"Steve","middle_name":"","last_name":"Cohen","suffix":"","nickname":"","district":"HD-TN-9","ftm_eid":6442808,"votesmart_id":24340,"opensecrets_id":"N00003225","knowwho_pid":198993,"ballotpedia":"Steve_Hobbs,_Missouri_Representative","bioguide_id":"C001068","sponsor_type_id":2,"sponsor_order":4,"committee_sponsor":0,"committee_id":0,"state_federal":0}],"sasts":[{"type_id":8,"type":"Related","sast_bill_number":"HB2912","sast_bill_id":1759599},{"type_id":8,"type":"Related","sast_bill_number":"HB3218","sast_bill_id":1764098},{"type_id":8,"type":"Related","sast_bill_number":"HB911","sast_bill_id":1702976},{"type_id":8,"type":"Related","sast_bill_number":"HB1049","sast_bill_id":1707837},{"type_id":8,"type":"Related","sast_bill_number":"HB1445","sast_bill_id":1731891},{"type_id":8,"type":"Related","sast_bill_number":"HB1716","sast_bill_id":1746071},{"type_id":8,"type":"Related","sast_bill_number":"HB2509","sast_bill_id":1754059},{"type_id":8,"type":"Related","sast_bill_number":"HB2558","sast_bill_id":1754495},{"type_id":8,"type":"Related","sast_bill_number":"HB3082","sast_bill_id":1761765},{"type_id":8,"type":"Related","sast_bill_number":"HB3593","sast_bill_id":1767439},{"type_id":8,"type":"Related","sast_bill_number":"HB3743","sast_bill_id":1768979},{"type_id":8,"type":"Related","sast_bill_number":"SB400","sast_bill_id":1707870},{"type_id":8,"type":"Related","sast_bill_number":"SB911","sast_bill_id":1746043},{"type_id":8,"type":"Related","sast_bill_number":"SB1255","sast_bill_id":1757962},{"type_id":8,"type":"Related","sast_bill_number":"SB1256","sast_bill_id":1759055},{"type_id":8,"type":"Related","sast_bill_number":"SB1459","sast_bill_id":1761548},{"type_id":8,"type":"Related","sast_bill_number":"SB1752","sast_bill_id":1766661},{"type_id":8,"type":"Related","sast_bill_number":"HB3780","sast_bill_id":1769581},{"type_id":8,"type":"Related","sast_bill_number":"HB3958","sast_bill_id":1771168},{"type_id":8,"type":"Related","sast_bill_number":"HB3969","sast_bill_id":1771215},{"type_id":8,"type":"Related","sast_bill_number":"HR597","sast_bill_id":1774693},{"type_id":8,"type":"Related","sast_bill_number":"HB4126","sast_bill_id":1771805},{"type_id":8,"type":"Related","sast_bill_number":"HB4021","sast_bill_id":1771362},{"type_id":8,"type":"Related","sast_bill_number":"HB4193","sast_bill_id":1772166},{"type_id":8,"type":"Related","sast_bill_number":"HB3983","sast_bill_id":1771227},{"type_id":8,"type":"Related","sast_bill_number":"HB3945","sast_bill_id":1771225},{"type_id":8,"type":"Related","sast_bill_number":"HB3796","sast_bill_id":1770205},{"type_id":8,"type":"Related","sast_bill_number":"HB4161","sast_bill_id":1772192},{"type_id":8,"type":"Related","sast_bill_number":"HB4082","sast_bill_id":1771525},{"type_id":8,"type":"Related","sast_bill_number":"SB2839","sast_bill_id":1778258},{"type_id":8,"type":"Related","sast_bill_number":"SB3331","sast_bill_id":1784118},{"type_id":8,"type":"Related","sast_bill_number":"HB7550","sast_bill_id":1860081},{"type_id":8,"type":"Related","sast_bill_number":"HB7696","sast_bill_id":1864754},{"type_id":8,"type":"Related","sast_bill_number":"SB3413","sast_bill_id":1790887},{"type_id":8,"type":"Related","sast_bill_number":"HB6627","sast_bill_id":1790880},{"type_id":8,"type":"Related","sast_bill_number":"HB2618","sast_bill_id":1755571},{"type_id":8,"type":"Related","sast_bill_number":"SB222","sast_bill_id":1691489},{"type_id":8,"type":"Related","sast_bill_number":"HB1804","sast_bill_id":1748517},{"type_id":8,"type":"Related","sast_bill_number":"SB1817","sast_bill_id":1770460},{"type_id":8,"type":"Related","sast_bill_number":"HB3559","sast_bill_id":1767461}],"subjects":[{"subject_id":13531,"subject_name":"Transportation and public works"}],"texts":[{"doc_id":2826265,"date":"2023-06-10","type":"Introduced","type_id":1,"mime":"application\/pdf","mime_id":2,"url":"https:\/\/legiscan.com\/US\/text\/HB3935\/id\/2826265","state_link":"https:\/\/www.congress.gov\/118\/bills\/hr3935\/BILLS-118hr3935ih.pdf","text_size":1471049,"text_hash":"3d15a36f118b6b517cb2361c5f6cd099","alt_bill_text":0,"alt_mime":"","alt_mime_id":0,"alt_state_link":"","alt_text_size":0,"alt_text_hash":""},{"doc_id":2833877,"date":"2023-07-12","type":"Introduced","type_id":1,"mime":"application\/pdf","mime_id":2,"url":"https:\/\/legiscan.com\/US\/text\/HB3935\/id\/2833877","state_link":"https:\/\/www.congress.gov\/118\/bills\/hr3935\/BILLS-118hr3935rh.pdf","text_size":1548289,"text_hash":"23f45bd5c5cdb06b13dbc6153420c30e","alt_bill_text":0,"alt_mime":"","alt_mime_id":0,"alt_state_link":"","alt_text_size":0,"alt_text_hash":""},{"doc_id":2835181,"date":"2023-07-26","type":"Engrossed","type_id":4,"mime":"application\/pdf","mime_id":2,"url":"https:\/\/legiscan.com\/US\/text\/HB3935\/id\/2835181","state_link":"https:\/\/www.congress.gov\/118\/bills\/hr3935\/BILLS-118hr3935eh.pdf","text_size":1507039,"text_hash":"18142c794977297565aaa4d5bdce05ea","alt_bill_text":0,"alt_mime":"","alt_mime_id":0,"alt_state_link":"","alt_text_size":0,"alt_text_hash":""},{"doc_id":2842480,"date":"2023-09-22","type":"Introduced","type_id":1,"mime":"application\/pdf","mime_id":2,"url":"https:\/\/legiscan.com\/US\/text\/HB3935\/id\/2842480","state_link":"https:\/\/www.congress.gov\/118\/bills\/hr3935\/BILLS-118hr3935pcs.pdf","text_size":1665896,"text_hash":"eb4a1a908679d2f189afb8523fd2dc8e","alt_bill_text":0,"alt_mime":"","alt_mime_id":0,"alt_state_link":"","alt_text_size":0,"alt_text_hash":""},{"doc_id":2995847,"date":"2024-05-10","type":"Amended","type_id":3,"mime":"application\/pdf","mime_id":2,"url":"https:\/\/legiscan.com\/US\/text\/HB3935\/id\/2995847","state_link":"https:\/\/www.congress.gov\/118\/bills\/hr3935\/BILLS-118hr3935eas.pdf","text_size":1396325,"text_hash":"b971166297c31ce49d5c31a2c68e8924","alt_bill_text":0,"alt_mime":"","alt_mime_id":0,"alt_state_link":"","alt_text_size":0,"alt_text_hash":""}],"votes":[{"roll_call_id":1350868,"date":"2023-07-19","desc":"On Agreeing to the Amendment RC# 341","yea":243,"nay":191,"nv":0,"absent":6,"total":440,"passed":1,"chamber":"H","chamber_id":114,"url":"https:\/\/legiscan.com\/US\/rollcall\/HB3935\/id\/1350868","state_link":"https:\/\/clerk.house.gov\/Votes\/2023341"},{"roll_call_id":1350869,"date":"2023-07-19","desc":"On Agreeing to the Amendment RC# 342","yea":203,"nay":231,"nv":0,"absent":6,"total":440,"passed":0,"chamber":"H","chamber_id":114,"url":"https:\/\/legiscan.com\/US\/rollcall\/HB3935\/id\/1350869","state_link":"https:\/\/clerk.house.gov\/Votes\/2023342"},{"roll_call_id":1350870,"date":"2023-07-19","desc":"On Agreeing to the Amendment RC# 343","yea":392,"nay":41,"nv":0,"absent":7,"total":440,"passed":1,"chamber":"H","chamber_id":114,"url":"https:\/\/legiscan.com\/US\/rollcall\/HB3935\/id\/1350870","state_link":"https:\/\/clerk.house.gov\/Votes\/2023343"},{"roll_call_id":1350871,"date":"2023-07-19","desc":"On Agreeing to the Amendment RC# 344","yea":193,"nay":236,"nv":0,"absent":11,"total":440,"passed":0,"chamber":"H","chamber_id":114,"url":"https:\/\/legiscan.com\/US\/rollcall\/HB3935\/id\/1350871","state_link":"https:\/\/clerk.house.gov\/Votes\/2023344"},{"roll_call_id":1350872,"date":"2023-07-19","desc":"On Agreeing to the Amendment RC# 345","yea":177,"nay":258,"nv":0,"absent":5,"total":440,"passed":0,"chamber":"H","chamber_id":114,"url":"https:\/\/legiscan.com\/US\/rollcall\/HB3935\/id\/1350872","state_link":"https:\/\/clerk.house.gov\/Votes\/2023345"},{"roll_call_id":1350873,"date":"2023-07-19","desc":"On Agreeing to the Amendment RC# 346","yea":141,"nay":294,"nv":0,"absent":5,"total":440,"passed":0,"chamber":"H","chamber_id":114,"url":"https:\/\/legiscan.com\/US\/rollcall\/HB3935\/id\/1350873","state_link":"https:\/\/clerk.house.gov\/Votes\/2023346"},{"roll_call_id":1350874,"date":"2023-07-19","desc":"On Agreeing to the Amendment RC# 347","yea":220,"nay":215,"nv":0,"absent":5,"total":440,"passed":1,"chamber":"H","chamber_id":114,"url":"https:\/\/legiscan.com\/US\/rollcall\/HB3935\/id\/1350874","state_link":"https:\/\/clerk.house.gov\/Votes\/2023347"},{"roll_call_id":1350875,"date":"2023-07-19","desc":"On Agreeing to the Amendment RC# 348","yea":214,"nay":219,"nv":0,"absent":7,"total":440,"passed":0,"chamber":"H","chamber_id":114,"url":"https:\/\/legiscan.com\/US\/rollcall\/HB3935\/id\/1350875","state_link":"https:\/\/clerk.house.gov\/Votes\/2023348"},{"roll_call_id":1350876,"date":"2023-07-19","desc":"On Agreeing to the Amendment RC# 349","yea":211,"nay":224,"nv":0,"absent":5,"total":440,"passed":0,"chamber":"H","chamber_id":114,"url":"https:\/\/legiscan.com\/US\/rollcall\/HB3935\/id\/1350876","state_link":"https:\/\/clerk.house.gov\/Votes\/2023349"},{"roll_call_id":1350877,"date":"2023-07-19","desc":"On Agreeing to the Amendment RC# 350","yea":240,"nay":195,"nv":0,"absent":5,"total":440,"passed":1,"chamber":"H","chamber_id":114,"url":"https:\/\/legiscan.com\/US\/rollcall\/HB3935\/id\/1350877","state_link":"https:\/\/clerk.house.gov\/Votes\/2023350"},{"roll_call_id":1350878,"date":"2023-07-19","desc":"On Agreeing to the Amendment RC# 351","yea":49,"nay":386,"nv":0,"absent":5,"total":440,"passed":0,"chamber":"H","chamber_id":114,"url":"https:\/\/legiscan.com\/US\/rollcall\/HB3935\/id\/1350878","state_link":"https:\/\/clerk.house.gov\/Votes\/2023351"},{"roll_call_id":1350879,"date":"2023-07-19","desc":"On Agreeing to the Amendment RC# 352","yea":216,"nay":219,"nv":0,"absent":5,"total":440,"passed":0,"chamber":"H","chamber_id":114,"url":"https:\/\/legiscan.com\/US\/rollcall\/HB3935\/id\/1350879","state_link":"https:\/\/clerk.house.gov\/Votes\/2023352"},{"roll_call_id":1350880,"date":"2023-07-19","desc":"On Agreeing to the Amendment RC# 353","yea":181,"nay":254,"nv":0,"absent":5,"total":440,"passed":0,"chamber":"H","chamber_id":114,"url":"https:\/\/legiscan.com\/US\/rollcall\/HB3935\/id\/1350880","state_link":"https:\/\/clerk.house.gov\/Votes\/2023353"},{"roll_call_id":1350881,"date":"2023-07-19","desc":"On Agreeing to the Amendment RC# 354","yea":229,"nay":205,"nv":0,"absent":6,"total":440,"passed":1,"chamber":"H","chamber_id":114,"url":"https:\/\/legiscan.com\/US\/rollcall\/HB3935\/id\/1350881","state_link":"https:\/\/clerk.house.gov\/Votes\/2023354"},{"roll_call_id":1350882,"date":"2023-07-19","desc":"On Agreeing to the Amendment RC# 355","yea":191,"nay":244,"nv":0,"absent":5,"total":440,"passed":0,"chamber":"H","chamber_id":114,"url":"https:\/\/legiscan.com\/US\/rollcall\/HB3935\/id\/1350882","state_link":"https:\/\/clerk.house.gov\/Votes\/2023355"},{"roll_call_id":1350883,"date":"2023-07-19","desc":"On Agreeing to the Amendment RC# 356","yea":206,"nay":227,"nv":0,"absent":7,"total":440,"passed":0,"chamber":"H","chamber_id":114,"url":"https:\/\/legiscan.com\/US\/rollcall\/HB3935\/id\/1350883","state_link":"https:\/\/clerk.house.gov\/Votes\/2023356"},{"roll_call_id":1350884,"date":"2023-07-19","desc":"On Agreeing to the Amendment RC# 357","yea":205,"nay":229,"nv":0,"absent":6,"total":440,"passed":0,"chamber":"H","chamber_id":114,"url":"https:\/\/legiscan.com\/US\/rollcall\/HB3935\/id\/1350884","state_link":"https:\/\/clerk.house.gov\/Votes\/2023357"},{"roll_call_id":1350885,"date":"2023-07-19","desc":"On Agreeing to the Amendment RC# 358","yea":127,"nay":308,"nv":0,"absent":5,"total":440,"passed":0,"chamber":"H","chamber_id":114,"url":"https:\/\/legiscan.com\/US\/rollcall\/HB3935\/id\/1350885","state_link":"https:\/\/clerk.house.gov\/Votes\/2023358"},{"roll_call_id":1350886,"date":"2023-07-19","desc":"On Agreeing to the Amendment RC# 359","yea":52,"nay":381,"nv":0,"absent":7,"total":440,"passed":0,"chamber":"H","chamber_id":114,"url":"https:\/\/legiscan.com\/US\/rollcall\/HB3935\/id\/1350886","state_link":"https:\/\/clerk.house.gov\/Votes\/2023359"},{"roll_call_id":1350887,"date":"2023-07-19","desc":"On Agreeing to the Amendment RC# 360","yea":45,"nay":387,"nv":0,"absent":8,"total":440,"passed":0,"chamber":"H","chamber_id":114,"url":"https:\/\/legiscan.com\/US\/rollcall\/HB3935\/id\/1350887","state_link":"https:\/\/clerk.house.gov\/Votes\/2023360"},{"roll_call_id":1350899,"date":"2023-07-20","desc":"On Agreeing to the Amendment RC# 361","yea":348,"nay":57,"nv":0,"absent":34,"total":439,"passed":1,"chamber":"H","chamber_id":114,"url":"https:\/\/legiscan.com\/US\/rollcall\/HB3935\/id\/1350899","state_link":"https:\/\/clerk.house.gov\/Votes\/2023361"},{"roll_call_id":1350900,"date":"2023-07-20","desc":"On Agreeing to the Amendment RC# 362","yea":64,"nay":329,"nv":0,"absent":46,"total":439,"passed":0,"chamber":"H","chamber_id":114,"url":"https:\/\/legiscan.com\/US\/rollcall\/HB3935\/id\/1350900","state_link":"https:\/\/clerk.house.gov\/Votes\/2023362"},{"roll_call_id":1350901,"date":"2023-07-20","desc":"On Agreeing to the Amendment RC# 363","yea":195,"nay":226,"nv":0,"absent":18,"total":439,"passed":0,"chamber":"H","chamber_id":114,"url":"https:\/\/legiscan.com\/US\/rollcall\/HB3935\/id\/1350901","state_link":"https:\/\/clerk.house.gov\/Votes\/2023363"},{"roll_call_id":1350902,"date":"2023-07-20","desc":"On Passage RC# 364","yea":351,"nay":69,"nv":0,"absent":13,"total":433,"passed":1,"chamber":"H","chamber_id":114,"url":"https:\/\/legiscan.com\/US\/rollcall\/HB3935\/id\/1350902","state_link":"https:\/\/clerk.house.gov\/Votes\/2023364"},{"roll_call_id":1362329,"date":"2023-09-26","desc":"On the Cloture Motion H.R. 3935 RC# 240","yea":77,"nay":19,"nv":0,"absent":4,"total":100,"passed":1,"chamber":"S","chamber_id":115,"url":"https:\/\/legiscan.com\/US\/rollcall\/HB3935\/id\/1362329","state_link":"https:\/\/www.senate.gov\/legislative\/LIS\/roll_call_votes\/vote1181\/vote_118_1_00240.htm"},{"roll_call_id":1362330,"date":"2023-09-28","desc":"On the Motion to Proceed H.R. 3935 RC# 241","yea":76,"nay":22,"nv":0,"absent":2,"total":100,"passed":1,"chamber":"S","chamber_id":115,"url":"https:\/\/legiscan.com\/US\/rollcall\/HB3935\/id\/1362330","state_link":"https:\/\/www.senate.gov\/legislative\/LIS\/roll_call_votes\/vote1181\/vote_118_1_00241.htm"},{"roll_call_id":1437908,"date":"2024-05-01","desc":"On Cloture on the Motion to Proceed H.R. 3935 RC# 157","yea":89,"nay":10,"nv":0,"absent":1,"total":100,"passed":1,"chamber":"S","chamber_id":115,"url":"https:\/\/legiscan.com\/US\/rollcall\/HB3935\/id\/1437908","state_link":"https:\/\/www.senate.gov\/legislative\/LIS\/roll_call_votes\/vote1182\/vote_118_2_00157.htm"},{"roll_call_id":1438886,"date":"2024-05-02","desc":"On the Motion to Proceed H.R. 3935 RC# 158","yea":81,"nay":10,"nv":0,"absent":9,"total":100,"passed":1,"chamber":"S","chamber_id":115,"url":"https:\/\/legiscan.com\/US\/rollcall\/HB3935\/id\/1438886","state_link":"https:\/\/www.senate.gov\/legislative\/LIS\/roll_call_votes\/vote1182\/vote_118_2_00158.htm"},{"roll_call_id":1441549,"date":"2024-05-08","desc":"On the Motion to Table H.R. 3935 RC# 160","yea":12,"nay":85,"nv":0,"absent":3,"total":100,"passed":0,"chamber":"S","chamber_id":115,"url":"https:\/\/legiscan.com\/US\/rollcall\/HB3935\/id\/1441549","state_link":"https:\/\/www.senate.gov\/legislative\/LIS\/roll_call_votes\/vote1182\/vote_118_2_00160.htm"},{"roll_call_id":1442062,"date":"2024-05-09","desc":"On the Cloture Motion H.R. 3935 RC# 161","yea":84,"nay":13,"nv":0,"absent":3,"total":100,"passed":1,"chamber":"S","chamber_id":115,"url":"https:\/\/legiscan.com\/US\/rollcall\/HB3935\/id\/1442062","state_link":"https:\/\/www.senate.gov\/legislative\/LIS\/roll_call_votes\/vote1182\/vote_118_2_00161.htm"},{"roll_call_id":1442063,"date":"2024-05-09","desc":"On Passage of the Bill H.R. 3935 RC# 162","yea":88,"nay":4,"nv":0,"absent":8,"total":100,"passed":1,"chamber":"S","chamber_id":115,"url":"https:\/\/legiscan.com\/US\/rollcall\/HB3935\/id\/1442063","state_link":"https:\/\/www.senate.gov\/legislative\/LIS\/roll_call_votes\/vote1182\/vote_118_2_00162.htm"}],"amendments":[],"supplements":[],"calendar":[{"type_id":1,"event_hash":"9d7b5679","type":"Hearing","date":"2023-06-13","time":"10:00","location":"2167 RHOB","description":"House Committee on Transportation and Infrastructure Hearing"},{"type_id":1,"event_hash":"774ea0bf","type":"Hearing","date":"2023-07-17","time":"16:00","location":"H-313, CAPITOL","description":"House Committee on Rules Hearing"}]}}